{
  "name_of_the_university": "Fleming College",
  "courses": [
    {
      "level": "Masters Certificate Program",
      "stream": "??",
      "degree": "??",
      "specialization": "??",
      "course_name": "Graduate Certificate in Global Business Management",
      "department/school": "??",
      "mode": "??",
      "duration": "2",
      "duration_type": "Years",
      "tuition_fees": "10,03,279",
      "tuition_fee_currency": "INR",
      "tuition_fee_duration_type": "Annual ",
      "application_fee": "95",
      "application_fee_currency": "CAD"
    },
    {
      "level": "Masters Certificate Program",
      "stream": "??",
      "degree": "??",
      "specialization": "??",
      "course_name": "Graduate Certificate in Wireless Information Networking",
      "department/school": "??",
      "mode": "??",
      "duration": "2",
      "duration_type": "Years",
      "tuition_fees": "10,40,013",
      "tuition_fee_currency": "INR",
      "tuition_fee_duration_type": "Annual ",
      "application_fee": "95",
      "application_fee_currency": "CAD"
    },
    {
      "level": "Masters Certificate Program",
      "stream": "??",
      "degree": "??",
      "specialization": "??",
      "course_name": "Graduate Certificate in Project Management",
      "department/school": "??",
      "mode": "??",
      "duration": "1",
      "duration_type": "Year",
      "tuition_fees": "10,08,170",
      "tuition_fee_currency": "INR",
      "tuition_fee_duration_type": "Annual ",
      "application_fee": "95",
      "application_fee_currency": "CAD"
    },
    {
      "level": "Bachelors Diploma Program",
      "stream": "??",
      "degree": "??",
      "specialization": "??",
      "course_name": "Advanced Diploma in Biotechnology",
      "department/school": "??",
      "mode": "??",
      "duration": "2.5",
      "duration_type": "Years",
      "tuition_fees": "10,03,279",
      "tuition_fee_currency": "INR",
      "tuition_fee_duration_type": "Annual ",
      "application_fee": "95",
      "application_fee_currency": "CAD"
    },
    {
      "level": "Bachelors Diploma Program",
      "stream": "??",
      "degree": "??",
      "specialization": "??",
      "course_name": "Diploma in Practical Nursing",
      "department/school": "??",
      "mode": "??",
      "duration": "2",
      "duration_type": "Years",
      "tuition_fees": "8,42,270",
      "tuition_fee_currency": "INR",
      "tuition_fee_duration_type": "Annual ",
      "application_fee": "95",
      "application_fee_currency": "CAD"
    },
    {
      "level": "Masters Certificate Program",
      "stream": "??",
      "degree": "??",
      "specialization": "??",
      "course_name": "Graduate Certificate in International Business Management",
      "department/school": "??",
      "mode": "??",
      "duration": "1",
      "duration_type": "Year",
      "tuition_fees": "10,03,279",
      "tuition_fee_currency": "INR",
      "tuition_fee_duration_type": "Annual ",
      "application_fee": "95",
      "application_fee_currency": "CAD"
    },
    {
      "level": "Bachelors Diploma Program",
      "stream": "??",
      "degree": "??",
      "specialization": "??",
      "course_name": "Diploma in Hospitality Management",
      "department/school": "??",
      "mode": "??",
      "duration": "2",
      "duration_type": "Years",
      "tuition_fees": "9,09,163",
      "tuition_fee_currency": "INR",
      "tuition_fee_duration_type": "Annual ",
      "application_fee": "95",
      "application_fee_currency": "CAD"
    },
    {
      "level": "Bachelors Diploma Program",
      "stream": "??",
      "degree": "??",
      "specialization": "??",
      "course_name": "Advanced Diploma in Computer Security and Investigations",
      "department/school": "??",
      "mode": "??",
      "duration": "3",
      "duration_type": "Years",
      "tuition_fees": "10,97,288",
      "tuition_fee_currency": "INR",
      "tuition_fee_duration_type": "Annual ",
      "application_fee": "95",
      "application_fee_currency": "CAD"
    },
    {
      "level": "Bachelors Diploma Program",
      "stream": "??",
      "degree": "??",
      "specialization": "??",
      "course_name": "Diploma in Instrumentation and Control Engineering Technician",
      "department/school": "??",
      "mode": "??",
      "duration": "2",
      "duration_type": "Years",
      "tuition_fees": "9,18,835",
      "tuition_fee_currency": "INR",
      "tuition_fee_duration_type": "Annual ",
      "application_fee": "95",
      "application_fee_currency": "CAD"
    },
    {
      "level": "Bachelors Diploma Program",
      "stream": "??",
      "degree": "??",
      "specialization": "??",
      "course_name": "Diploma in Electrical Engineering Technician",
      "department/school": "??",
      "mode": "??",
      "duration": "2",
      "duration_type": "Years",
      "tuition_fees": "9,09,815",
      "tuition_fee_currency": "INR",
      "tuition_fee_duration_type": "Annual ",
      "application_fee": "95",
      "application_fee_currency": "CAD"
    },
    {
      "level": "Bachelors Diploma Program",
      "stream": "??",
      "degree": "??",
      "specialization": "??",
      "course_name": "Diploma in Business Administration - Human Resources Management",
      "department/school": "??",
      "mode": "??",
      "duration": "3",
      "duration_type": "Years",
      "tuition_fees": "9,09,815",
      "tuition_fee_currency": "INR",
      "tuition_fee_duration_type": "Annual ",
      "application_fee": "95",
      "application_fee_currency": "CAD"
    },
    {
      "level": "Bachelors Diploma Program",
      "stream": "??",
      "degree": "??",
      "specialization": "??",
      "course_name": "Advanced Diploma in Computer Engineering Technology",
      "department/school": "??",
      "mode": "??",
      "duration": "3",
      "duration_type": "Years",
      "tuition_fees": "9,18,835",
      "tuition_fee_currency": "INR",
      "tuition_fee_duration_type": "Annual ",
      "application_fee": "95",
      "application_fee_currency": "CAD"
    },
    {
      "level": "Bachelors Certificate Program",
      "stream": "??",
      "degree": "??",
      "specialization": "??",
      "course_name": "Certificate in Electrical Techniques",
      "department/school": "??",
      "mode": "??",
      "duration": "1",
      "duration_type": "Year",
      "tuition_fees": "9,21,226",
      "tuition_fee_currency": "INR",
      "tuition_fee_duration_type": "Annual ",
      "application_fee": "95",
      "application_fee_currency": "CAD"
    },
    {
      "level": "Masters Certificate Program",
      "stream": "??",
      "degree": "??",
      "specialization": "??",
      "course_name": "Graduate Certificate in Geographic Information Systems-Application Specialist",
      "department/school": "??",
      "mode": "??",
      "duration": "10",
      "duration_type": "Months",
      "tuition_fees": "9,35,789",
      "tuition_fee_currency": "INR",
      "tuition_fee_duration_type": "Annual ",
      "application_fee": "95",
      "application_fee_currency": "CAD"
    },
    {
      "level": "Bachelors Diploma Program",
      "stream": "??",
      "degree": "??",
      "specialization": "??",
      "course_name": "Diploma in Business Administration-Marketing",
      "department/school": "??",
      "mode": "??",
      "duration": "3",
      "duration_type": "Years",
      "tuition_fees": "9,09,815",
      "tuition_fee_currency": "INR",
      "tuition_fee_duration_type": "Annual ",
      "application_fee": "95",
      "application_fee_currency": "CAD"
    },
    {
      "level": "Bachelors Diploma Program",
      "stream": "??",
      "degree": "??",
      "specialization": "??",
      "course_name": "Advanced Diploma in Graphic Design - Visual Communication",
      "department/school": "??",
      "mode": "??",
      "duration": "3",
      "duration_type": "Years",
      "tuition_fees": "9,65,024",
      "tuition_fee_currency": "INR",
      "tuition_fee_duration_type": "Annual ",
      "application_fee": "95",
      "application_fee_currency": "CAD"
    },
    {
      "level": "Bachelors Diploma Program",
      "stream": "??",
      "degree": "??",
      "specialization": "??",
      "course_name": "Advanced Diploma in Business Administration",
      "department/school": "??",
      "mode": "??",
      "duration": "3",
      "duration_type": "Years",
      "tuition_fees": "9,09,815",
      "tuition_fee_currency": "INR",
      "tuition_fee_duration_type": "Annual ",
      "application_fee": "95",
      "application_fee_currency": "CAD"
    }
  ]
}