{
  "University of Plymouth ": {
    "name_of_the_university": "University of Plymouth ",
    "short_name": "",
    "establishment_year": "1992",
    "institute_type": "Public University",
    "country": "UK",
    "state": "Devon",
    "city": "Plymouth",
    "website": "https://www.plymouth.ac.uk/international/how-to-apply/international-students-country-guides/india",
    "phone_no": "+91 9769938844",
    "fax": "",
    "email_address": " india@plymouth.ac.uk",
    "main_campus_address": "Drake Circus, Plymouth PL4 8AA, UK",
    "latitude": "50.3759",
    "longitude": "-4.1396",
    "logo": "https://images.shiksha.com/mediadata/images/1550044093phpSeR18E.png",
    "brochure": "",
    "no_of_programs": "16",
    "no_of_international_students": "3,000",
    "international_student_%": "",
    "on_campus_hostel_availability": "Yes",
    "hostel_fee": 370000.0,
    "hostel_fee_currency": "INR",
    "qs_ranking": "651-700",
    "qs_ranking_year": "2020",
    "times_higher_education": "501-600",
    "times_higher_education_year": "2020",
    "usnews": "516",
    "usnews_year": "2020",
    "intake_month": "",
    "intake_month_1": "",
    "intake_month_2": ""
  },
  "Stamford International University ": {
    "name_of_the_university": "Stamford International University ",
    "short_name": "",
    "establishment_year": "1955",
    "institute_type": "Public College",
    "country": "Thailand",
    "state": "",
    "city": "Bangkok",
    "website": "http://www.stamford.edu/ContactUs",
    "phone_no": "+66(0)2 7694000",
    "fax": "",
    "email_address": "international@stamford.edu",
    "main_campus_address": "16, Motorway Road \u2013 Km 2, Prawet, Bangkok 10250 Thailand",
    "latitude": "",
    "longitude": "",
    "logo": "https://images.shiksha.com/mediadata/images/1549884669phpqXFeyV.png",
    "brochure": "",
    "no_of_programs": "3",
    "no_of_international_students": "",
    "international_student_%": "",
    "on_campus_hostel_availability": "No",
    "hostel_fee": "",
    "hostel_fee_currency": "",
    "qs_ranking": "",
    "qs_ranking_year": "",
    "times_higher_education": "",
    "times_higher_education_year": "",
    "usnews": "",
    "usnews_year": "",
    "intake_month": "",
    "intake_month_1": "",
    "intake_month_2": ""
  },
  "University of Colorado Boulder": {
    "name_of_the_university": "University of Colorado Boulder",
    "short_name": "",
    "establishment_year": "1876",
    "institute_type": "Public University",
    "country": "USA",
    "state": "Colorado",
    "city": "Boulder",
    "website": "http://www.colorado.edu/admissions/undergraduate/contact/international",
    "phone_no": "+1-303-492-6216",
    "fax": "",
    "email_address": "natalie.koster@colorado.edu",
    "main_campus_address": "Regent Administrative Center 125,552 UCB\nBoulder, Colorado 80309-0552",
    "latitude": "40.0076",
    "longitude": "-105.2659",
    "logo": "https://images.shiksha.com/mediadata/images/1411391170phpxbAJ6K.jpeg",
    "brochure": "",
    "no_of_programs": "5",
    "no_of_international_students": "3,135",
    "international_student_%": "9 %",
    "on_campus_hostel_availability": "Yes",
    "hostel_fee": 509999.99999999994,
    "hostel_fee_currency": "INR",
    "qs_ranking": "206",
    "qs_ranking_year": "2020",
    "times_higher_education": "124",
    "times_higher_education_year": "2020",
    "usnews": "50",
    "usnews_year": "2020",
    "intake_month": "",
    "intake_month_1": "",
    "intake_month_2": ""
  },
  "Eastern Illinois University ": {
    "name_of_the_university": "Eastern Illinois University ",
    "short_name": "",
    "establishment_year": "1895",
    "institute_type": "Public University",
    "country": "USA",
    "state": "Illinois",
    "city": "Charleston",
    "website": "https://www.eiu.edu/interntl/",
    "phone_no": "(217)581-2321",
    "fax": "",
    "email_address": "international@eiu.edu",
    "main_campus_address": "600 Lincoln Avenue\nCharleston, IL 61920-3099",
    "latitude": "39.4837",
    "longitude": "-88.1752",
    "logo": "https://images.shiksha.com/mediadata/images/1549861050phpcz7sLx.png",
    "brochure": "",
    "no_of_programs": "19",
    "no_of_international_students": "433",
    "international_student_%": "5.8 %",
    "on_campus_hostel_availability": "Yes",
    "hostel_fee": 700000.0,
    "hostel_fee_currency": "INR",
    "qs_ranking": "",
    "qs_ranking_year": "",
    "times_higher_education": "",
    "times_higher_education_year": "",
    "usnews": "40",
    "usnews_year": "2020",
    "intake_month": "May",
    "intake_month_1": "Oct",
    "intake_month_2": ""
  },
  "Blue Mountains International Hotel Management School ": {
    "name_of_the_university": "Blue Mountains International Hotel Management School ",
    "short_name": "",
    "establishment_year": "1991",
    "institute_type": "Private College",
    "country": "Australia",
    "state": "New South Wales",
    "city": "Sydney",
    "website": "http://www.bluemountains.edu.au/about-us/laureate/",
    "phone_no": "+61 2 9307 4600",
    "fax": "",
    "email_address": "admissions@bluemountains.edu.au",
    "main_campus_address": "540 George Street,Sydney,New South Wales,2000 Australia",
    "latitude": "-35.307 ",
    "longitude": "149.134",
    "logo": "https://images.shiksha.com/mediadata/images/1549968142phpi4kOv1.png",
    "brochure": "",
    "no_of_programs": "5",
    "no_of_international_students": "",
    "international_student_%": "",
    "on_campus_hostel_availability": "No",
    "hostel_fee": "",
    "hostel_fee_currency": "",
    "qs_ranking": "",
    "qs_ranking_year": "",
    "times_higher_education": "",
    "times_higher_education_year": "",
    "usnews": "",
    "usnews_year": "",
    "intake_month": "",
    "intake_month_1": "",
    "intake_month_2": ""
  },
  "UCL institute of Education ": {
    "name_of_the_university": "UCL institute of Education ",
    "short_name": "",
    "establishment_year": "2014",
    "institute_type": "Public College",
    "country": "UK",
    "state": "London",
    "city": "London",
    "website": "",
    "phone_no": "",
    "fax": "",
    "email_address": "",
    "main_campus_address": "",
    "latitude": "",
    "longitude": "",
    "logo": "https://images.shiksha.com/mediadata/images/1493971152phpBs6lhE.png",
    "brochure": "",
    "no_of_programs": "9",
    "no_of_international_students": "",
    "international_student_%": "",
    "on_campus_hostel_availability": "Yes",
    "hostel_fee": 570000.0,
    "hostel_fee_currency": "INR",
    "qs_ranking": "",
    "qs_ranking_year": "",
    "times_higher_education": "",
    "times_higher_education_year": "",
    "usnews": "",
    "usnews_year": "",
    "intake_month": "",
    "intake_month_1": "",
    "intake_month_2": ""
  }
}