{
  "name_of_the_university": "UCSI University",
  "courses": [
    {
      "level": "Masters Program",
      "stream": "??",
      "degree": "??",
      "specialization": "??",
      "course_name": "MSc Food Science",
      "department/school": "??",
      "mode": "??",
      "duration": "1.5",
      "duration_type": "Years",
      "tuition_fees": "4,27,035",
      "tuition_fee_currency": "INR",
      "tuition_fee_duration_type": "Annual ",
      "application_fee": "3,100",
      "application_fee_currency": "MYR"
    },
    {
      "level": "Bachelors Program",
      "stream": "??",
      "degree": "??",
      "specialization": "??",
      "course_name": "BA (Hons) Business Administration",
      "department/school": "??",
      "mode": "??",
      "duration": "3",
      "duration_type": "Years",
      "tuition_fees": "3,37,096",
      "tuition_fee_currency": "INR",
      "tuition_fee_duration_type": "Annual ",
      "application_fee": "3,100",
      "application_fee_currency": "MYR"
    },
    {
      "level": "Bachelors Diploma Program",
      "stream": "??",
      "degree": "??",
      "specialization": "??",
      "course_name": "Diploma in Fashion Design",
      "department/school": "??",
      "mode": "??",
      "duration": "2",
      "duration_type": "Years",
      "tuition_fees": "3,71,799",
      "tuition_fee_currency": "INR",
      "tuition_fee_duration_type": "Annual ",
      "application_fee": "3,100",
      "application_fee_currency": "MYR"
    },
    {
      "level": "Bachelors Program",
      "stream": "??",
      "degree": "??",
      "specialization": "??",
      "course_name": "BSc (Hons) Finance & Investment",
      "department/school": "??",
      "mode": "??",
      "duration": "3",
      "duration_type": "Years",
      "tuition_fees": "2,90,035",
      "tuition_fee_currency": "INR",
      "tuition_fee_duration_type": "Annual ",
      "application_fee": "3,100",
      "application_fee_currency": "MYR"
    },
    {
      "level": "Bachelors Diploma Program",
      "stream": "??",
      "degree": "??",
      "specialization": "??",
      "course_name": "Diploma in Information Technology",
      "department/school": "??",
      "mode": "??",
      "duration": "2",
      "duration_type": "Years",
      "tuition_fees": "2,44,717",
      "tuition_fee_currency": "INR",
      "tuition_fee_duration_type": "Annual ",
      "application_fee": "3,100",
      "application_fee_currency": "MYR"
    },
    {
      "level": "Bachelors Program",
      "stream": "??",
      "degree": "??",
      "specialization": "??",
      "course_name": "Bachelor of Computer Science (Hons) Mobile Computing and Networking",
      "department/school": "??",
      "mode": "??",
      "duration": "3",
      "duration_type": "Years",
      "tuition_fees": "2,91,778",
      "tuition_fee_currency": "INR",
      "tuition_fee_duration_type": "Annual ",
      "application_fee": "3,100",
      "application_fee_currency": "MYR"
    },
    {
      "level": "Masters Program",
      "stream": "??",
      "degree": "??",
      "specialization": "??",
      "course_name": "MBA",
      "department/school": "??",
      "mode": "??",
      "duration": "1",
      "duration_type": "Year",
      "tuition_fees": "6,10,050",
      "tuition_fee_currency": "INR",
      "tuition_fee_duration_type": "Annual ",
      "application_fee": "3,100",
      "application_fee_currency": "MYR"
    },
    {
      "level": "Masters Program",
      "stream": "??",
      "degree": "??",
      "specialization": "??",
      "course_name": "MSc Food Science with Business Management",
      "department/school": "??",
      "mode": "??",
      "duration": "1.5",
      "duration_type": "Years",
      "tuition_fees": "4,16,873",
      "tuition_fee_currency": "INR",
      "tuition_fee_duration_type": "Annual ",
      "application_fee": "3,100",
      "application_fee_currency": "MYR"
    },
    {
      "level": "Masters Program",
      "stream": "??",
      "degree": "??",
      "specialization": "??",
      "course_name": "Master of Arts in English Language And Communication",
      "department/school": "??",
      "mode": "??",
      "duration": "2",
      "duration_type": "Years",
      "tuition_fees": "3,13,740",
      "tuition_fee_currency": "INR",
      "tuition_fee_duration_type": "Annual ",
      "application_fee": "3,100",
      "application_fee_currency": "MYR"
    },
    {
      "level": "Masters Program",
      "stream": "??",
      "degree": "??",
      "specialization": "??",
      "course_name": "MSc in Technopreneurship",
      "department/school": "??",
      "mode": "??",
      "duration": "1",
      "duration_type": "Year",
      "tuition_fees": "6,76,720",
      "tuition_fee_currency": "INR",
      "tuition_fee_duration_type": "Annual ",
      "application_fee": "3,100",
      "application_fee_currency": "MYR"
    },
    {
      "level": "Masters Program",
      "stream": "??",
      "degree": "??",
      "specialization": "??",
      "course_name": "MBA with special focus in Blue Ocean Strategy (BOS)",
      "department/school": "??",
      "mode": "??",
      "duration": "1.5",
      "duration_type": "Years",
      "tuition_fees": "6,97,200",
      "tuition_fee_currency": "INR",
      "tuition_fee_duration_type": "Annual ",
      "application_fee": "3,100",
      "application_fee_currency": "MYR"
    },
    {
      "level": "Bachelors Program",
      "stream": "??",
      "degree": "??",
      "specialization": "??",
      "course_name": "BEng (Hons) Communication & Electronic Engineering",
      "department/school": "??",
      "mode": "??",
      "duration": "4",
      "duration_type": "Years",
      "tuition_fees": "2,36,177",
      "tuition_fee_currency": "INR",
      "tuition_fee_duration_type": "Annual ",
      "application_fee": "3,100",
      "application_fee_currency": "MYR"
    },
    {
      "level": "Bachelors Program",
      "stream": "??",
      "degree": "??",
      "specialization": "??",
      "course_name": "BEng (Hons) Civil Engineering",
      "department/school": "??",
      "mode": "??",
      "duration": "4",
      "duration_type": "Years",
      "tuition_fees": "3,30,821",
      "tuition_fee_currency": "INR",
      "tuition_fee_duration_type": "Annual ",
      "application_fee": "3,100",
      "application_fee_currency": "MYR"
    },
    {
      "level": "Masters Program",
      "stream": "??",
      "degree": "??",
      "specialization": "??",
      "course_name": "MSc Biotechnology",
      "department/school": "??",
      "mode": "??",
      "duration": "1.5",
      "duration_type": "Years",
      "tuition_fees": "4,16,873",
      "tuition_fee_currency": "INR",
      "tuition_fee_duration_type": "Annual ",
      "application_fee": "3,100",
      "application_fee_currency": "MYR"
    },
    {
      "level": "Bachelors Program",
      "stream": "??",
      "degree": "??",
      "specialization": "??",
      "course_name": "BA (Hons) Accounting & Finance",
      "department/school": "??",
      "mode": "??",
      "duration": "3",
      "duration_type": "Years",
      "tuition_fees": "2,84,806",
      "tuition_fee_currency": "INR",
      "tuition_fee_duration_type": "Annual ",
      "application_fee": "3,100",
      "application_fee_currency": "MYR"
    },
    {
      "level": "Bachelors Program",
      "stream": "??",
      "degree": "??",
      "specialization": "??",
      "course_name": "BA (Hons) in Fashion Design with Marketing",
      "department/school": "??",
      "mode": "??",
      "duration": "3",
      "duration_type": "Years",
      "tuition_fees": "4,37,144",
      "tuition_fee_currency": "INR",
      "tuition_fee_duration_type": "Annual ",
      "application_fee": "3,100",
      "application_fee_currency": "MYR"
    },
    {
      "level": "Bachelors Program",
      "stream": "??",
      "degree": "??",
      "specialization": "??",
      "course_name": "BEng (Hons) Mechatronic Engineering",
      "department/school": "??",
      "mode": "??",
      "duration": "4",
      "duration_type": "Years",
      "tuition_fees": "3,67,686",
      "tuition_fee_currency": "INR",
      "tuition_fee_duration_type": "Annual ",
      "application_fee": "3,100",
      "application_fee_currency": "MYR"
    },
    {
      "level": "Bachelors Program",
      "stream": "??",
      "degree": "??",
      "specialization": "??",
      "course_name": "BEng (Hons) Mechanical Engineering",
      "department/school": "??",
      "mode": "??",
      "duration": "4",
      "duration_type": "Years",
      "tuition_fees": "3,06,419",
      "tuition_fee_currency": "INR",
      "tuition_fee_duration_type": "Annual ",
      "application_fee": "3,100",
      "application_fee_currency": "MYR"
    },
    {
      "level": "Bachelors Program",
      "stream": "??",
      "degree": "??",
      "specialization": "??",
      "course_name": "BSc (Hons) Biotechnology",
      "department/school": "??",
      "mode": "??",
      "duration": "3",
      "duration_type": "Years",
      "tuition_fees": "4,46,644",
      "tuition_fee_currency": "INR",
      "tuition_fee_duration_type": "Annual ",
      "application_fee": "3,100",
      "application_fee_currency": "MYR"
    },
    {
      "level": "Bachelors Program",
      "stream": "??",
      "degree": "??",
      "specialization": "??",
      "course_name": "BEng (Hons) Electrical & Electronic Engineering",
      "department/school": "??",
      "mode": "??",
      "duration": "4",
      "duration_type": "Years",
      "tuition_fees": "2,36,177",
      "tuition_fee_currency": "INR",
      "tuition_fee_duration_type": "Annual ",
      "application_fee": "3,100",
      "application_fee_currency": "MYR"
    },
    {
      "level": "Bachelors Program",
      "stream": "??",
      "degree": "??",
      "specialization": "??",
      "course_name": "Bachelor of Hospitality Administration  ",
      "department/school": "??",
      "mode": "??",
      "duration": "3",
      "duration_type": "Years",
      "tuition_fees": "3,76,802",
      "tuition_fee_currency": "INR",
      "tuition_fee_duration_type": "Annual ",
      "application_fee": "3,100",
      "application_fee_currency": "MYR"
    },
    {
      "level": "Bachelors Program",
      "stream": "??",
      "degree": "??",
      "specialization": "??",
      "course_name": "BA (Hons) in Event & Tourism Management",
      "department/school": "??",
      "mode": "??",
      "duration": "3",
      "duration_type": "Years",
      "tuition_fees": "2,56,604",
      "tuition_fee_currency": "INR",
      "tuition_fee_duration_type": "Annual ",
      "application_fee": "3,100",
      "application_fee_currency": "MYR"
    },
    {
      "level": "Bachelors Diploma Program",
      "stream": "??",
      "degree": "??",
      "specialization": "??",
      "course_name": "Diploma in Hotel Management ",
      "department/school": "??",
      "mode": "??",
      "duration": "2",
      "duration_type": "Years",
      "tuition_fees": "3,82,414",
      "tuition_fee_currency": "INR",
      "tuition_fee_duration_type": "Annual ",
      "application_fee": "3,100",
      "application_fee_currency": "MYR"
    },
    {
      "level": "Bachelors Program",
      "stream": "??",
      "degree": "??",
      "specialization": "??",
      "course_name": "BCA (Hons) in 3D Animation Design",
      "department/school": "??",
      "mode": "??",
      "duration": "3",
      "duration_type": "Years",
      "tuition_fees": "4,60,501",
      "tuition_fee_currency": "INR",
      "tuition_fee_duration_type": "Annual ",
      "application_fee": "3,100",
      "application_fee_currency": "MYR"
    },
    {
      "level": "Bachelors Program",
      "stream": "??",
      "degree": "??",
      "specialization": "??",
      "course_name": "BA (Hons) English Language and Communication",
      "department/school": "??",
      "mode": "??",
      "duration": "3",
      "duration_type": "Years",
      "tuition_fees": "3,27,510",
      "tuition_fee_currency": "INR",
      "tuition_fee_duration_type": "Annual ",
      "application_fee": "3,100",
      "application_fee_currency": "MYR"
    },
    {
      "level": "Masters Program",
      "stream": "??",
      "degree": "??",
      "specialization": "??",
      "course_name": "MSc Electrical Engineering",
      "department/school": "??",
      "mode": "??",
      "duration": "1",
      "duration_type": "Year",
      "tuition_fees": "6,27,480",
      "tuition_fee_currency": "INR",
      "tuition_fee_duration_type": "Annual ",
      "application_fee": "3,100",
      "application_fee_currency": "MYR"
    },
    {
      "level": "Bachelors Program",
      "stream": "??",
      "degree": "??",
      "specialization": "??",
      "course_name": "BA (Hons) in Graphic Design",
      "department/school": "??",
      "mode": "??",
      "duration": "3",
      "duration_type": "Years",
      "tuition_fees": "3,90,258",
      "tuition_fee_currency": "INR",
      "tuition_fee_duration_type": "Annual ",
      "application_fee": "3,100",
      "application_fee_currency": "MYR"
    },
    {
      "level": "Bachelors Diploma Program",
      "stream": "??",
      "degree": "??",
      "specialization": "??",
      "course_name": "Diploma in 3D Animation Design",
      "department/school": "??",
      "mode": "??",
      "duration": "2",
      "duration_type": "Years",
      "tuition_fees": "3,24,634",
      "tuition_fee_currency": "INR",
      "tuition_fee_duration_type": "Annual ",
      "application_fee": "3,100",
      "application_fee_currency": "MYR"
    },
    {
      "level": "Bachelors Diploma Program",
      "stream": "??",
      "degree": "??",
      "specialization": "??",
      "course_name": "Diploma in Graphic Design",
      "department/school": "??",
      "mode": "??",
      "duration": "2",
      "duration_type": "Years",
      "tuition_fees": "3,24,634",
      "tuition_fee_currency": "INR",
      "tuition_fee_duration_type": "Annual ",
      "application_fee": "3,100",
      "application_fee_currency": "MYR"
    },
    {
      "level": "Masters Program",
      "stream": "??",
      "degree": "??",
      "specialization": "??",
      "course_name": "MSc Biotechnology with Business Management",
      "department/school": "??",
      "mode": "??",
      "duration": "1.5",
      "duration_type": "Years",
      "tuition_fees": "4,16,873",
      "tuition_fee_currency": "INR",
      "tuition_fee_duration_type": "Annual ",
      "application_fee": "3,100",
      "application_fee_currency": "MYR"
    },
    {
      "level": "Bachelors Program",
      "stream": "??",
      "degree": "??",
      "specialization": "??",
      "course_name": "Bachelor of Financial Economics (Hons)",
      "department/school": "??",
      "mode": "??",
      "duration": "3",
      "duration_type": "Years",
      "tuition_fees": "2,84,806",
      "tuition_fee_currency": "INR",
      "tuition_fee_duration_type": "Annual ",
      "application_fee": "3,100",
      "application_fee_currency": "MYR"
    },
    {
      "level": "Bachelors Program",
      "stream": "??",
      "degree": "??",
      "specialization": "??",
      "course_name": "BA (Hons) Accounting",
      "department/school": "??",
      "mode": "??",
      "duration": "3",
      "duration_type": "Years",
      "tuition_fees": "2,84,806",
      "tuition_fee_currency": "INR",
      "tuition_fee_duration_type": "Annual ",
      "application_fee": "3,100",
      "application_fee_currency": "MYR"
    },
    {
      "level": "Bachelors Program",
      "stream": "??",
      "degree": "??",
      "specialization": "??",
      "course_name": "BA (Hons) Branding and Advertising",
      "department/school": "??",
      "mode": "??",
      "duration": "3",
      "duration_type": "Years",
      "tuition_fees": "3,10,951",
      "tuition_fee_currency": "INR",
      "tuition_fee_duration_type": "Annual ",
      "application_fee": "3,100",
      "application_fee_currency": "MYR"
    },
    {
      "level": "Bachelors Program",
      "stream": "??",
      "degree": "??",
      "specialization": "??",
      "course_name": "BA (Hons) Marketing",
      "department/school": "??",
      "mode": "??",
      "duration": "3",
      "duration_type": "Years",
      "tuition_fees": "3,63,241",
      "tuition_fee_currency": "INR",
      "tuition_fee_duration_type": "Annual ",
      "application_fee": "3,100",
      "application_fee_currency": "MYR"
    },
    {
      "level": "Bachelors Diploma Program",
      "stream": "??",
      "degree": "??",
      "specialization": "??",
      "course_name": "Diploma in Management",
      "department/school": "??",
      "mode": "??",
      "duration": "2",
      "duration_type": "Years",
      "tuition_fees": "2,97,007",
      "tuition_fee_currency": "INR",
      "tuition_fee_duration_type": "Annual ",
      "application_fee": "3,100",
      "application_fee_currency": "MYR"
    },
    {
      "level": "PhD Program",
      "stream": "??",
      "degree": "??",
      "specialization": "??",
      "course_name": "Doctorate of Philosophy (Science)",
      "department/school": "??",
      "mode": "??",
      "duration": "2-5",
      "duration_type": "Years",
      "tuition_fees": "3,93,918",
      "tuition_fee_currency": "INR",
      "tuition_fee_duration_type": "Annual ",
      "application_fee": "3,100",
      "application_fee_currency": "MYR"
    },
    {
      "level": "Masters Program",
      "stream": "??",
      "degree": "??",
      "specialization": "??",
      "course_name": "MSc Applied Sciences",
      "department/school": "??",
      "mode": "??",
      "duration": "1.5",
      "duration_type": "Years",
      "tuition_fees": "2,00,009",
      "tuition_fee_currency": "INR",
      "tuition_fee_duration_type": "Annual ",
      "application_fee": "3,100",
      "application_fee_currency": "MYR"
    },
    {
      "level": "Bachelors Program",
      "stream": "??",
      "degree": "??",
      "specialization": "??",
      "course_name": " BA (Hons) in Hospitality Management",
      "department/school": "??",
      "mode": "??",
      "duration": "3",
      "duration_type": "Years",
      "tuition_fees": "3,01,853",
      "tuition_fee_currency": "INR",
      "tuition_fee_duration_type": "Annual ",
      "application_fee": "3,100",
      "application_fee_currency": "MYR"
    },
    {
      "level": "Bachelors Program",
      "stream": "??",
      "degree": "??",
      "specialization": "??",
      "course_name": "BA (Hons) Mass Communication",
      "department/school": "??",
      "mode": "??",
      "duration": "3",
      "duration_type": "Years",
      "tuition_fees": "4,48,648",
      "tuition_fee_currency": "INR",
      "tuition_fee_duration_type": "Annual ",
      "application_fee": "3,100",
      "application_fee_currency": "MYR"
    }
  ]
}