{
  "name_of_the_university": "Edge Hill University",
  "courses": [
    {
      "level": "Masters Program",
      "stream": "??",
      "degree": "??",
      "specialization": "??",
      "course_name": "MBA Business Administration (Finance)",
      "department/school": "??",
      "mode": "??",
      "duration": "1",
      "duration_type": "Year",
      "tuition_fees": "12,73,085",
      "tuition_fee_currency": "INR",
      "tuition_fee_duration_type": "Annual ",
      "application_fee": "20",
      "application_fee_currency": "Pound"
    },
    {
      "level": "Masters Program",
      "stream": "??",
      "degree": "??",
      "specialization": "??",
      "course_name": "MBA Business Administration (Human Resource Management)",
      "department/school": "??",
      "mode": "??",
      "duration": "1",
      "duration_type": "Year",
      "tuition_fees": "12,73,085",
      "tuition_fee_currency": "INR",
      "tuition_fee_duration_type": "Annual ",
      "application_fee": "20",
      "application_fee_currency": "Pound"
    },
    {
      "level": "Bachelors Program",
      "stream": "??",
      "degree": "??",
      "specialization": "??",
      "course_name": "LLB (Hons) Law",
      "department/school": "??",
      "mode": "??",
      "duration": "3",
      "duration_type": "Years",
      "tuition_fees": "10,30,483",
      "tuition_fee_currency": "INR",
      "tuition_fee_duration_type": "Annual ",
      "application_fee": "20",
      "application_fee_currency": "Pound"
    },
    {
      "level": "Bachelors Program",
      "stream": "??",
      "degree": "??",
      "specialization": "??",
      "course_name": "BSc (Hons) Computing (Systems and Software)",
      "department/school": "??",
      "mode": "??",
      "duration": "3-4",
      "duration_type": "Years",
      "tuition_fees": "10,30,483",
      "tuition_fee_currency": "INR",
      "tuition_fee_duration_type": "Annual ",
      "application_fee": "20",
      "application_fee_currency": "Pound"
    },
    {
      "level": "Bachelors Program",
      "stream": "??",
      "degree": "??",
      "specialization": "??",
      "course_name": "BSc (Hons) Midwifery",
      "department/school": "??",
      "mode": "??",
      "duration": "3",
      "duration_type": "Years",
      "tuition_fees": "10,30,483",
      "tuition_fee_currency": "INR",
      "tuition_fee_duration_type": "Annual ",
      "application_fee": "20",
      "application_fee_currency": "Pound"
    },
    {
      "level": "Masters Program",
      "stream": "??",
      "degree": "??",
      "specialization": "??",
      "course_name": "MBA Master of Business Administration(Marketing)",
      "department/school": "??",
      "mode": "??",
      "duration": "1",
      "duration_type": "Year",
      "tuition_fees": "12,73,085",
      "tuition_fee_currency": "INR",
      "tuition_fee_duration_type": "Annual ",
      "application_fee": "20",
      "application_fee_currency": "Pound"
    },
    {
      "level": "Masters Program",
      "stream": "??",
      "degree": "??",
      "specialization": "??",
      "course_name": "MBA Business Administration (Information Technology)",
      "department/school": "??",
      "mode": "??",
      "duration": "1",
      "duration_type": "Year",
      "tuition_fees": "12,73,085",
      "tuition_fee_currency": "INR",
      "tuition_fee_duration_type": "Annual ",
      "application_fee": "20",
      "application_fee_currency": "Pound"
    },
    {
      "level": "Masters Program",
      "stream": "??",
      "degree": "??",
      "specialization": "??",
      "course_name": "MSc Information Security and IT Management",
      "department/school": "??",
      "mode": "??",
      "duration": "12",
      "duration_type": "Years",
      "tuition_fees": "11,78,355",
      "tuition_fee_currency": "INR",
      "tuition_fee_duration_type": "Annual ",
      "application_fee": "20",
      "application_fee_currency": "Pound"
    },
    {
      "level": "Masters Program",
      "stream": "??",
      "degree": "??",
      "specialization": "??",
      "course_name": "MBA Business Administration",
      "department/school": "??",
      "mode": "??",
      "duration": "1",
      "duration_type": "Year",
      "tuition_fees": "12,73,085",
      "tuition_fee_currency": "INR",
      "tuition_fee_duration_type": "Annual ",
      "application_fee": "20",
      "application_fee_currency": "Pound"
    },
    {
      "level": "Masters Program",
      "stream": "??",
      "degree": "??",
      "specialization": "??",
      "course_name": "MA Creative Writing",
      "department/school": "??",
      "mode": "??",
      "duration": "1",
      "duration_type": "Year",
      "tuition_fees": "12,24,565",
      "tuition_fee_currency": "INR",
      "tuition_fee_duration_type": "Annual ",
      "application_fee": "20",
      "application_fee_currency": "Pound"
    },
    {
      "level": "Bachelors Program",
      "stream": "??",
      "degree": "??",
      "specialization": "??",
      "course_name": "LLB (Hons) Law with Politics",
      "department/school": "??",
      "mode": "??",
      "duration": "3",
      "duration_type": "Years",
      "tuition_fees": "10,30,483",
      "tuition_fee_currency": "INR",
      "tuition_fee_duration_type": "Annual ",
      "application_fee": "20",
      "application_fee_currency": "Pound"
    },
    {
      "level": "Masters Program",
      "stream": "??",
      "degree": "??",
      "specialization": "??",
      "course_name": "MSc Computing",
      "department/school": "??",
      "mode": "??",
      "duration": "1",
      "duration_type": "Year",
      "tuition_fees": "12,24,565",
      "tuition_fee_currency": "INR",
      "tuition_fee_duration_type": "Annual ",
      "application_fee": "20",
      "application_fee_currency": "Pound"
    },
    {
      "level": "Bachelors Program",
      "stream": "??",
      "degree": "??",
      "specialization": "??",
      "course_name": "BA (Hons) Film Studies",
      "department/school": "??",
      "mode": "??",
      "duration": "3",
      "duration_type": "Years",
      "tuition_fees": "11,09,040",
      "tuition_fee_currency": "INR",
      "tuition_fee_duration_type": "Annual ",
      "application_fee": "20",
      "application_fee_currency": "Pound"
    },
    {
      "level": "Bachelors Program",
      "stream": "??",
      "degree": "??",
      "specialization": "??",
      "course_name": "BSc (Hons) Computing (Application Development)",
      "department/school": "??",
      "mode": "??",
      "duration": "3-4",
      "duration_type": "Years",
      "tuition_fees": "10,69,761",
      "tuition_fee_currency": "INR",
      "tuition_fee_duration_type": "Annual ",
      "application_fee": "20",
      "application_fee_currency": "Pound"
    },
    {
      "level": "Bachelors Program",
      "stream": "??",
      "degree": "??",
      "specialization": "??",
      "course_name": "BSc (Hons) Computing (Networking, Security and Forensics)",
      "department/school": "??",
      "mode": "??",
      "duration": "3",
      "duration_type": "Years",
      "tuition_fees": "11,09,040",
      "tuition_fee_currency": "INR",
      "tuition_fee_duration_type": "Annual ",
      "application_fee": "20",
      "application_fee_currency": "Pound"
    },
    {
      "level": "Masters Program",
      "stream": "??",
      "degree": "??",
      "specialization": "??",
      "course_name": "MA English",
      "department/school": "??",
      "mode": "??",
      "duration": "1",
      "duration_type": "Year",
      "tuition_fees": "12,24,565",
      "tuition_fee_currency": "INR",
      "tuition_fee_duration_type": "Annual ",
      "application_fee": "20",
      "application_fee_currency": "Pound"
    },
    {
      "level": "Bachelors Program",
      "stream": "??",
      "degree": "??",
      "specialization": "??",
      "course_name": "BSc (Hons) Business and Management",
      "department/school": "??",
      "mode": "??",
      "duration": "3",
      "duration_type": "Years",
      "tuition_fees": "11,09,040",
      "tuition_fee_currency": "INR",
      "tuition_fee_duration_type": "Annual ",
      "application_fee": "20",
      "application_fee_currency": "Pound"
    },
    {
      "level": "Masters Program",
      "stream": "??",
      "degree": "??",
      "specialization": "??",
      "course_name": "MSc Cyber Security",
      "department/school": "??",
      "mode": "??",
      "duration": "1",
      "duration_type": "Year",
      "tuition_fees": "12,24,565",
      "tuition_fee_currency": "INR",
      "tuition_fee_duration_type": "Annual ",
      "application_fee": "20",
      "application_fee_currency": "Pound"
    },
    {
      "level": "Bachelors Program",
      "stream": "??",
      "degree": "??",
      "specialization": "??",
      "course_name": "BA (Hons) Criminology and Criminal Justice",
      "department/school": "??",
      "mode": "??",
      "duration": "3",
      "duration_type": "Years",
      "tuition_fees": "10,30,483",
      "tuition_fee_currency": "INR",
      "tuition_fee_duration_type": "Annual ",
      "application_fee": "20",
      "application_fee_currency": "Pound"
    },
    {
      "level": "Masters Program",
      "stream": "??",
      "degree": "??",
      "specialization": "??",
      "course_name": "MA Marketing Communications and Branding",
      "department/school": "??",
      "mode": "??",
      "duration": "1",
      "duration_type": "Year",
      "tuition_fees": "11,78,355",
      "tuition_fee_currency": "INR",
      "tuition_fee_duration_type": "Annual ",
      "application_fee": "20",
      "application_fee_currency": "Pound"
    },
    {
      "level": "Masters Program",
      "stream": "??",
      "degree": "??",
      "specialization": "??",
      "course_name": "MSc Big Data Analytics",
      "department/school": "??",
      "mode": "??",
      "duration": "1",
      "duration_type": "Year",
      "tuition_fees": "12,24,565",
      "tuition_fee_currency": "INR",
      "tuition_fee_duration_type": "Annual ",
      "application_fee": "20",
      "application_fee_currency": "Pound"
    },
    {
      "level": "Bachelors Program",
      "stream": "??",
      "degree": "??",
      "specialization": "??",
      "course_name": "BSc (Hons) Information Technology Management for Business",
      "department/school": "??",
      "mode": "??",
      "duration": "3",
      "duration_type": "Years",
      "tuition_fees": "11,09,040",
      "tuition_fee_currency": "INR",
      "tuition_fee_duration_type": "Annual ",
      "application_fee": "20",
      "application_fee_currency": "Pound"
    },
    {
      "level": "Bachelors Program",
      "stream": "??",
      "degree": "??",
      "specialization": "??",
      "course_name": "BA (Hons) Animation",
      "department/school": "??",
      "mode": "??",
      "duration": "3",
      "duration_type": "Years",
      "tuition_fees": "11,09,040",
      "tuition_fee_currency": "INR",
      "tuition_fee_duration_type": "Annual ",
      "application_fee": "20",
      "application_fee_currency": "Pound"
    },
    {
      "level": "Bachelors Program",
      "stream": "??",
      "degree": "??",
      "specialization": "??",
      "course_name": "BSc (Hons) Biology",
      "department/school": "??",
      "mode": "??",
      "duration": "3",
      "duration_type": "Years",
      "tuition_fees": "11,09,040",
      "tuition_fee_currency": "INR",
      "tuition_fee_duration_type": "Annual ",
      "application_fee": "20",
      "application_fee_currency": "Pound"
    },
    {
      "level": "Bachelors Program",
      "stream": "??",
      "degree": "??",
      "specialization": "??",
      "course_name": "BSc (Hons) Computing",
      "department/school": "??",
      "mode": "??",
      "duration": "3",
      "duration_type": "Years",
      "tuition_fees": "11,09,040",
      "tuition_fee_currency": "INR",
      "tuition_fee_duration_type": "Annual ",
      "application_fee": "20",
      "application_fee_currency": "Pound"
    },
    {
      "level": "Bachelors Program",
      "stream": "??",
      "degree": "??",
      "specialization": "??",
      "course_name": "BSc (Hons) Genetics",
      "department/school": "??",
      "mode": "??",
      "duration": "3",
      "duration_type": "Years",
      "tuition_fees": "11,09,040",
      "tuition_fee_currency": "INR",
      "tuition_fee_duration_type": "Annual ",
      "application_fee": "20",
      "application_fee_currency": "Pound"
    },
    {
      "level": "Bachelors Program",
      "stream": "??",
      "degree": "??",
      "specialization": "??",
      "course_name": "BSc (Hons) Ecology and Conservation",
      "department/school": "??",
      "mode": "??",
      "duration": "3",
      "duration_type": "Years",
      "tuition_fees": "10,90,556",
      "tuition_fee_currency": "INR",
      "tuition_fee_duration_type": "Annual ",
      "application_fee": "20",
      "application_fee_currency": "Pound"
    },
    {
      "level": "Bachelors Program",
      "stream": "??",
      "degree": "??",
      "specialization": "??",
      "course_name": "BSc (Hons) Human Biololgy",
      "department/school": "??",
      "mode": "??",
      "duration": "3",
      "duration_type": "Years",
      "tuition_fees": "11,32,145",
      "tuition_fee_currency": "INR",
      "tuition_fee_duration_type": "Annual ",
      "application_fee": "20",
      "application_fee_currency": "Pound"
    },
    {
      "level": "Bachelors Program",
      "stream": "??",
      "degree": "??",
      "specialization": "??",
      "course_name": "BSc (Hons) Web Design and Development",
      "department/school": "??",
      "mode": "??",
      "duration": "3",
      "duration_type": "Years",
      "tuition_fees": "11,09,040",
      "tuition_fee_currency": "INR",
      "tuition_fee_duration_type": "Annual ",
      "application_fee": "20",
      "application_fee_currency": "Pound"
    },
    {
      "level": "Masters Program",
      "stream": "??",
      "degree": "??",
      "specialization": "??",
      "course_name": "MSc Psychology in Business",
      "department/school": "??",
      "mode": "??",
      "duration": "1",
      "duration_type": "Year",
      "tuition_fees": "12,24,565",
      "tuition_fee_currency": "INR",
      "tuition_fee_duration_type": "Annual ",
      "application_fee": "20",
      "application_fee_currency": "Pound"
    },
    {
      "level": "Bachelors Program",
      "stream": "??",
      "degree": "??",
      "specialization": "??",
      "course_name": "BSc (Hons) Accountancy",
      "department/school": "??",
      "mode": "??",
      "duration": "3",
      "duration_type": "Years",
      "tuition_fees": "11,32,145",
      "tuition_fee_currency": "INR",
      "tuition_fee_duration_type": "Annual ",
      "application_fee": "20",
      "application_fee_currency": "Pound"
    },
    {
      "level": "Bachelors Program",
      "stream": "??",
      "degree": "??",
      "specialization": "??",
      "course_name": "BA (Hons) Criminiology with Law",
      "department/school": "??",
      "mode": "??",
      "duration": "3",
      "duration_type": "Years",
      "tuition_fees": "10,30,483",
      "tuition_fee_currency": "INR",
      "tuition_fee_duration_type": "Annual ",
      "application_fee": "20",
      "application_fee_currency": "Pound"
    },
    {
      "level": "Masters Program",
      "stream": "??",
      "degree": "??",
      "specialization": "??",
      "course_name": "MSc Advanced Computer Networking",
      "department/school": "??",
      "mode": "??",
      "duration": "1",
      "duration_type": "Year",
      "tuition_fees": "12,24,565",
      "tuition_fee_currency": "INR",
      "tuition_fee_duration_type": "Annual ",
      "application_fee": "20",
      "application_fee_currency": "Pound"
    },
    {
      "level": "Bachelors Program",
      "stream": "??",
      "degree": "??",
      "specialization": "??",
      "course_name": "BA (Hons) Creative Writing",
      "department/school": "??",
      "mode": "??",
      "duration": "3",
      "duration_type": "Years",
      "tuition_fees": "11,09,040",
      "tuition_fee_currency": "INR",
      "tuition_fee_duration_type": "Annual ",
      "application_fee": "20",
      "application_fee_currency": "Pound"
    },
    {
      "level": "Bachelors Program",
      "stream": "??",
      "degree": "??",
      "specialization": "??",
      "course_name": "BA (Hons) English Language",
      "department/school": "??",
      "mode": "??",
      "duration": "3",
      "duration_type": "Years",
      "tuition_fees": "11,09,040",
      "tuition_fee_currency": "INR",
      "tuition_fee_duration_type": "Annual ",
      "application_fee": "20",
      "application_fee_currency": "Pound"
    },
    {
      "level": "Bachelors Program",
      "stream": "??",
      "degree": "??",
      "specialization": "??",
      "course_name": "BSc (Hons) Marketing with Digital Communications",
      "department/school": "??",
      "mode": "??",
      "duration": "3",
      "duration_type": "Years",
      "tuition_fees": "11,32,145",
      "tuition_fee_currency": "INR",
      "tuition_fee_duration_type": "Annual ",
      "application_fee": "20",
      "application_fee_currency": "Pound"
    },
    {
      "level": "Bachelors Program",
      "stream": "??",
      "degree": "??",
      "specialization": "??",
      "course_name": "BA (Hons) English",
      "department/school": "??",
      "mode": "??",
      "duration": "3",
      "duration_type": "Years",
      "tuition_fees": "11,09,040",
      "tuition_fee_currency": "INR",
      "tuition_fee_duration_type": "Annual ",
      "application_fee": "20",
      "application_fee_currency": "Pound"
    },
    {
      "level": "Bachelors Program",
      "stream": "??",
      "degree": "??",
      "specialization": "??",
      "course_name": "BA (Hons) History",
      "department/school": "??",
      "mode": "??",
      "duration": "3",
      "duration_type": "Years",
      "tuition_fees": "11,09,040",
      "tuition_fee_currency": "INR",
      "tuition_fee_duration_type": "Annual ",
      "application_fee": "20",
      "application_fee_currency": "Pound"
    },
    {
      "level": "Bachelors Program",
      "stream": "??",
      "degree": "??",
      "specialization": "??",
      "course_name": "BSc (Hons) Marketing with Advertising",
      "department/school": "??",
      "mode": "??",
      "duration": "3",
      "duration_type": "Years",
      "tuition_fees": "11,09,040",
      "tuition_fee_currency": "INR",
      "tuition_fee_duration_type": "Annual ",
      "application_fee": "20",
      "application_fee_currency": "Pound"
    },
    {
      "level": "Bachelors Program",
      "stream": "??",
      "degree": "??",
      "specialization": "??",
      "course_name": "BSc (Hons) Computing (Information Systems)",
      "department/school": "??",
      "mode": "??",
      "duration": "3-4",
      "duration_type": "Years",
      "tuition_fees": "10,69,761",
      "tuition_fee_currency": "INR",
      "tuition_fee_duration_type": "Annual ",
      "application_fee": "20",
      "application_fee_currency": "Pound"
    },
    {
      "level": "Bachelors Program",
      "stream": "??",
      "degree": "??",
      "specialization": "??",
      "course_name": "BA (Hons) Advertising",
      "department/school": "??",
      "mode": "??",
      "duration": "3",
      "duration_type": "Years",
      "tuition_fees": "10,69,761",
      "tuition_fee_currency": "INR",
      "tuition_fee_duration_type": "Annual ",
      "application_fee": "20",
      "application_fee_currency": "Pound"
    },
    {
      "level": "Bachelors Program",
      "stream": "??",
      "degree": "??",
      "specialization": "??",
      "course_name": "BSc (Hons) Computing (Games Programming)",
      "department/school": "??",
      "mode": "??",
      "duration": "3",
      "duration_type": "Years",
      "tuition_fees": "11,09,040",
      "tuition_fee_currency": "INR",
      "tuition_fee_duration_type": "Annual ",
      "application_fee": "20",
      "application_fee_currency": "Pound"
    },
    {
      "level": "Bachelors Program",
      "stream": "??",
      "degree": "??",
      "specialization": "??",
      "course_name": "BSc (Hons) Business and Management with Human Resource Management",
      "department/school": "??",
      "mode": "??",
      "duration": "3",
      "duration_type": "Years",
      "tuition_fees": "11,32,145",
      "tuition_fee_currency": "INR",
      "tuition_fee_duration_type": "Annual ",
      "application_fee": "20",
      "application_fee_currency": "Pound"
    },
    {
      "level": "Masters Program",
      "stream": "??",
      "degree": "??",
      "specialization": "??",
      "course_name": "MA History and Culture",
      "department/school": "??",
      "mode": "??",
      "duration": "1",
      "duration_type": "Year",
      "tuition_fees": "12,24,565",
      "tuition_fee_currency": "INR",
      "tuition_fee_duration_type": "Annual ",
      "application_fee": "20",
      "application_fee_currency": "Pound"
    },
    {
      "level": "Bachelors Program",
      "stream": "??",
      "degree": "??",
      "specialization": "??",
      "course_name": "BSc (Hons) Computing (Mobile and Embedded Systems)",
      "department/school": "??",
      "mode": "??",
      "duration": "3-4",
      "duration_type": "Years",
      "tuition_fees": "10,30,483",
      "tuition_fee_currency": "INR",
      "tuition_fee_duration_type": "Annual ",
      "application_fee": "20",
      "application_fee_currency": "Pound"
    },
    {
      "level": "Bachelors Program",
      "stream": "??",
      "degree": "??",
      "specialization": "??",
      "course_name": "BSc (Hons) Business and Economics",
      "department/school": "??",
      "mode": "??",
      "duration": "3",
      "duration_type": "Years",
      "tuition_fees": "11,09,040",
      "tuition_fee_currency": "INR",
      "tuition_fee_duration_type": "Annual ",
      "application_fee": "20",
      "application_fee_currency": "Pound"
    },
    {
      "level": "Bachelors Program",
      "stream": "??",
      "degree": "??",
      "specialization": "??",
      "course_name": "BSc (Hons) Marketing",
      "department/school": "??",
      "mode": "??",
      "duration": "3",
      "duration_type": "Years",
      "tuition_fees": "11,32,145",
      "tuition_fee_currency": "INR",
      "tuition_fee_duration_type": "Annual ",
      "application_fee": "20",
      "application_fee_currency": "Pound"
    }
  ]
}