{
  "name_of_the_university": "Maryville University",
  "courses": [
    {
      "level": "Masters Program",
      "stream": "??",
      "degree": "??",
      "specialization": "??",
      "course_name": "M.S. Data Science",
      "department/school": "??",
      "mode": "??",
      "duration": "1.5-2",
      "duration_type": "Years",
      "tuition_fees": "9,68,707",
      "tuition_fee_currency": "INR",
      "tuition_fee_duration_type": "Annual ",
      "application_fee": "Fees",
      "application_fee_currency": "No"
    },
    {
      "level": "Masters Program",
      "stream": "??",
      "degree": "??",
      "specialization": "??",
      "course_name": "Master of Business Administration",
      "department/school": "??",
      "mode": "??",
      "duration": "1",
      "duration_type": "Year",
      "tuition_fees": "18,61,125",
      "tuition_fee_currency": "INR",
      "tuition_fee_duration_type": "Annual ",
      "application_fee": "Fees",
      "application_fee_currency": "No"
    },
    {
      "level": "Masters Program",
      "stream": "??",
      "degree": "??",
      "specialization": "??",
      "course_name": "Master of Arts in Strategic Communication and Leadership",
      "department/school": "??",
      "mode": "??",
      "duration": "1.5-2",
      "duration_type": "Years",
      "tuition_fees": "9,67,005",
      "tuition_fee_currency": "INR",
      "tuition_fee_duration_type": "Annual ",
      "application_fee": "Fees",
      "application_fee_currency": "No"
    },
    {
      "level": "Masters Program",
      "stream": "??",
      "degree": "??",
      "specialization": "??",
      "course_name": "MA Education \u2013 Teacher as Leader",
      "department/school": "??",
      "mode": "??",
      "duration": "1.5-2",
      "duration_type": "Years",
      "tuition_fees": "5,45,717",
      "tuition_fee_currency": "INR",
      "tuition_fee_duration_type": "Annual ",
      "application_fee": "Fees",
      "application_fee_currency": "No"
    },
    {
      "level": "Masters Program",
      "stream": "??",
      "degree": "??",
      "specialization": "??",
      "course_name": "MS Actuarial Science",
      "department/school": "??",
      "mode": "??",
      "duration": "1.5-2",
      "duration_type": "Years",
      "tuition_fees": "11,62,406",
      "tuition_fee_currency": "INR",
      "tuition_fee_duration_type": "Annual ",
      "application_fee": "Fees",
      "application_fee_currency": "No"
    },
    {
      "level": "Bachelors Program",
      "stream": "??",
      "degree": "??",
      "specialization": "??",
      "course_name": "B.S in Applied Statistics and Data Analytics",
      "department/school": "??",
      "mode": "??",
      "duration": "4",
      "duration_type": "Years",
      "tuition_fees": "18,48,363",
      "tuition_fee_currency": "INR",
      "tuition_fee_duration_type": "Annual ",
      "application_fee": "Fees",
      "application_fee_currency": "No"
    },
    {
      "level": "Bachelors Program",
      "stream": "??",
      "degree": "??",
      "specialization": "??",
      "course_name": "Bachelor of Science in Actuarial Science",
      "department/school": "??",
      "mode": "??",
      "duration": "4",
      "duration_type": "Years",
      "tuition_fees": "18,48,363",
      "tuition_fee_currency": "INR",
      "tuition_fee_duration_type": "Annual ",
      "application_fee": "Fees",
      "application_fee_currency": "No"
    },
    {
      "level": "Bachelors Program",
      "stream": "??",
      "degree": "??",
      "specialization": "??",
      "course_name": "Bachelor of Science in Management and Leadership",
      "department/school": "??",
      "mode": "??",
      "duration": "4",
      "duration_type": "Years",
      "tuition_fees": "18,48,363",
      "tuition_fee_currency": "INR",
      "tuition_fee_duration_type": "Annual ",
      "application_fee": "Fees",
      "application_fee_currency": "No"
    },
    {
      "level": "Bachelors Program",
      "stream": "??",
      "degree": "??",
      "specialization": "??",
      "course_name": "Bachelors in Humanities",
      "department/school": "??",
      "mode": "??",
      "duration": "2-3",
      "duration_type": "Years",
      "tuition_fees": "8,75,402",
      "tuition_fee_currency": "INR",
      "tuition_fee_duration_type": "Annual ",
      "application_fee": "Fees",
      "application_fee_currency": "No"
    },
    {
      "level": "Bachelors Program",
      "stream": "??",
      "degree": "??",
      "specialization": "??",
      "course_name": "Bachelor of Science in Cybersecurity",
      "department/school": "??",
      "mode": "??",
      "duration": "4",
      "duration_type": "Years",
      "tuition_fees": "18,48,363",
      "tuition_fee_currency": "INR",
      "tuition_fee_duration_type": "Annual ",
      "application_fee": "Fees",
      "application_fee_currency": "No"
    },
    {
      "level": "Bachelors Program",
      "stream": "??",
      "degree": "??",
      "specialization": "??",
      "course_name": "B.S. in Biology with Biomedical Science Concentration",
      "department/school": "??",
      "mode": "??",
      "duration": "4",
      "duration_type": "Years",
      "tuition_fees": "18,48,363",
      "tuition_fee_currency": "INR",
      "tuition_fee_duration_type": "Annual ",
      "application_fee": "Fees",
      "application_fee_currency": "No"
    },
    {
      "level": "Bachelors Program",
      "stream": "??",
      "degree": "??",
      "specialization": "??",
      "course_name": "Bachelor of Arts in Healthcare Practice Management",
      "department/school": "??",
      "mode": "??",
      "duration": "4",
      "duration_type": "Years",
      "tuition_fees": "18,12,062",
      "tuition_fee_currency": "INR",
      "tuition_fee_duration_type": "Annual ",
      "application_fee": "Fees",
      "application_fee_currency": "No"
    },
    {
      "level": "Bachelors Program",
      "stream": "??",
      "degree": "??",
      "specialization": "??",
      "course_name": "B.S. in Biochemistry",
      "department/school": "??",
      "mode": "??",
      "duration": "4",
      "duration_type": "Years",
      "tuition_fees": "18,48,363",
      "tuition_fee_currency": "INR",
      "tuition_fee_duration_type": "Annual ",
      "application_fee": "Fees",
      "application_fee_currency": "No"
    },
    {
      "level": "Bachelors Program",
      "stream": "??",
      "degree": "??",
      "specialization": "??",
      "course_name": "B.F.A. in Interactive Design",
      "department/school": "??",
      "mode": "??",
      "duration": "4",
      "duration_type": "Years",
      "tuition_fees": "18,48,363",
      "tuition_fee_currency": "INR",
      "tuition_fee_duration_type": "Annual ",
      "application_fee": "Fees",
      "application_fee_currency": "No"
    },
    {
      "level": "Bachelors Program",
      "stream": "??",
      "degree": "??",
      "specialization": "??",
      "course_name": "Bachelor of Science in Game Design",
      "department/school": "??",
      "mode": "??",
      "duration": "4",
      "duration_type": "Years",
      "tuition_fees": "18,48,363",
      "tuition_fee_currency": "INR",
      "tuition_fee_duration_type": "Annual ",
      "application_fee": "Fees",
      "application_fee_currency": "No"
    },
    {
      "level": "Bachelors Program",
      "stream": "??",
      "degree": "??",
      "specialization": "??",
      "course_name": "Bachelor of Science in Business Administration",
      "department/school": "??",
      "mode": "??",
      "duration": "4",
      "duration_type": "Years",
      "tuition_fees": "18,48,363",
      "tuition_fee_currency": "INR",
      "tuition_fee_duration_type": "Annual ",
      "application_fee": "Fees",
      "application_fee_currency": "No"
    },
    {
      "level": "Bachelors Program",
      "stream": "??",
      "degree": "??",
      "specialization": "??",
      "course_name": "Bachelor of Science in Accounting",
      "department/school": "??",
      "mode": "??",
      "duration": "4",
      "duration_type": "Years",
      "tuition_fees": "18,48,363",
      "tuition_fee_currency": "INR",
      "tuition_fee_duration_type": "Annual ",
      "application_fee": "Fees",
      "application_fee_currency": "No"
    },
    {
      "level": "Bachelors Program",
      "stream": "??",
      "degree": "??",
      "specialization": "??",
      "course_name": "B.F.A. Graphic Design",
      "department/school": "??",
      "mode": "??",
      "duration": "4",
      "duration_type": "Years",
      "tuition_fees": "18,48,363",
      "tuition_fee_currency": "INR",
      "tuition_fee_duration_type": "Annual ",
      "application_fee": "Fees",
      "application_fee_currency": "No"
    },
    {
      "level": "Bachelors Program",
      "stream": "??",
      "degree": "??",
      "specialization": "??",
      "course_name": "Bachelor of Science in Management Information Systems",
      "department/school": "??",
      "mode": "??",
      "duration": "4",
      "duration_type": "Years",
      "tuition_fees": "18,48,363",
      "tuition_fee_currency": "INR",
      "tuition_fee_duration_type": "Annual ",
      "application_fee": "Fees",
      "application_fee_currency": "No"
    },
    {
      "level": "Bachelors Program",
      "stream": "??",
      "degree": "??",
      "specialization": "??",
      "course_name": "Bachelor of Science in Financial Services",
      "department/school": "??",
      "mode": "??",
      "duration": "4",
      "duration_type": "Years",
      "tuition_fees": "18,48,363",
      "tuition_fee_currency": "INR",
      "tuition_fee_duration_type": "Annual ",
      "application_fee": "Fees",
      "application_fee_currency": "No"
    }
  ]
}