{
  "name_of_the_university": "Northwestern Michigan College",
  "courses": [
    {
      "level": "Bachelors Program",
      "stream": "??",
      "degree": "??",
      "specialization": "??",
      "course_name": "Business Administration (BS) - Aviation",
      "department/school": "??",
      "mode": "??",
      "duration": "4",
      "duration_type": "Years",
      "tuition_fees": "5,30,048",
      "tuition_fee_currency": "INR",
      "tuition_fee_duration_type": "Annual ",
      "application_fee": "Fees",
      "application_fee_currency": "No"
    },
    {
      "level": "Bachelors Program",
      "stream": "??",
      "degree": "??",
      "specialization": "??",
      "course_name": " Associate in Applied Science degree - Biology",
      "department/school": "??",
      "mode": "??",
      "duration": "2",
      "duration_type": "Years",
      "tuition_fees": "7,10,418",
      "tuition_fee_currency": "INR",
      "tuition_fee_duration_type": "Annual ",
      "application_fee": "Fees",
      "application_fee_currency": "No"
    },
    {
      "level": "Bachelors Program",
      "stream": "??",
      "degree": "??",
      "specialization": "??",
      "course_name": "Associate Degree in Engineering Technology",
      "department/school": "??",
      "mode": "??",
      "duration": "2",
      "duration_type": "Years",
      "tuition_fees": "7,10,418",
      "tuition_fee_currency": "INR",
      "tuition_fee_duration_type": "Annual ",
      "application_fee": "Fees",
      "application_fee_currency": "No"
    },
    {
      "level": "Bachelors Program",
      "stream": "??",
      "degree": "??",
      "specialization": "??",
      "course_name": "Associate in Applied Science degree - Computer Information Technology - Developer",
      "department/school": "??",
      "mode": "??",
      "duration": "2",
      "duration_type": "Years",
      "tuition_fees": "7,34,099",
      "tuition_fee_currency": "INR",
      "tuition_fee_duration_type": "Annual ",
      "application_fee": "Fees",
      "application_fee_currency": "No"
    },
    {
      "level": "Bachelors Program",
      "stream": "??",
      "degree": "??",
      "specialization": "??",
      "course_name": "Associate in Applied Science degree - Business Administration",
      "department/school": "??",
      "mode": "??",
      "duration": "2",
      "duration_type": "Years",
      "tuition_fees": "7,10,418",
      "tuition_fee_currency": "INR",
      "tuition_fee_duration_type": "Annual ",
      "application_fee": "Fees",
      "application_fee_currency": "No"
    },
    {
      "level": "Bachelors Program",
      "stream": "??",
      "degree": "??",
      "specialization": "??",
      "course_name": "Associate in Science and Arts Degree - Engineering",
      "department/school": "??",
      "mode": "??",
      "duration": "2",
      "duration_type": "Years",
      "tuition_fees": "3,78,890",
      "tuition_fee_currency": "INR",
      "tuition_fee_duration_type": "Annual ",
      "application_fee": "Fees",
      "application_fee_currency": "No"
    },
    {
      "level": "Bachelors Program",
      "stream": "??",
      "degree": "??",
      "specialization": "??",
      "course_name": "Associate in Science and Arts Degree - Arts/Fine Arts",
      "department/school": "??",
      "mode": "??",
      "duration": "2",
      "duration_type": "Years",
      "tuition_fees": "7,10,418",
      "tuition_fee_currency": "INR",
      "tuition_fee_duration_type": "Annual ",
      "application_fee": "Fees",
      "application_fee_currency": "No"
    },
    {
      "level": "Bachelors Program",
      "stream": "??",
      "degree": "??",
      "specialization": "??",
      "course_name": "Associate in Applied Science Degree in Aviation",
      "department/school": "??",
      "mode": "??",
      "duration": "2",
      "duration_type": "Years",
      "tuition_fees": "7,57,779",
      "tuition_fee_currency": "INR",
      "tuition_fee_duration_type": "Annual ",
      "application_fee": "Fees",
      "application_fee_currency": "No"
    },
    {
      "level": "Bachelors Program",
      "stream": "??",
      "degree": "??",
      "specialization": "??",
      "course_name": "Associate in Applied Science degree - Computer Information Technology - Infrastructure",
      "department/school": "??",
      "mode": "??",
      "duration": "2",
      "duration_type": "Years",
      "tuition_fees": "7,81,460",
      "tuition_fee_currency": "INR",
      "tuition_fee_duration_type": "Annual ",
      "application_fee": "Fees",
      "application_fee_currency": "No"
    },
    {
      "level": "Bachelors Program",
      "stream": "??",
      "degree": "??",
      "specialization": "??",
      "course_name": "Associate in Science and Arts Degree - Chemistry",
      "department/school": "??",
      "mode": "??",
      "duration": "2",
      "duration_type": "Years",
      "tuition_fees": "7,10,418",
      "tuition_fee_currency": "INR",
      "tuition_fee_duration_type": "Annual ",
      "application_fee": "Fees",
      "application_fee_currency": "No"
    },
    {
      "level": "Bachelors Program",
      "stream": "??",
      "degree": "??",
      "specialization": "??",
      "course_name": "Bachelor of Science - Marine Technology Major",
      "department/school": "??",
      "mode": "??",
      "duration": "4",
      "duration_type": "Years",
      "tuition_fees": "10,37,976",
      "tuition_fee_currency": "INR",
      "tuition_fee_duration_type": "Annual ",
      "application_fee": "Fees",
      "application_fee_currency": "No"
    },
    {
      "level": "Bachelors Program",
      "stream": "??",
      "degree": "??",
      "specialization": "??",
      "course_name": "Associate in Applied Science Degree - Accounting",
      "department/school": "??",
      "mode": "??",
      "duration": "2",
      "duration_type": "Years",
      "tuition_fees": "7,22,258",
      "tuition_fee_currency": "INR",
      "tuition_fee_duration_type": "Annual ",
      "application_fee": "Fees",
      "application_fee_currency": "No"
    }
  ]
}