{
  "name_of_the_university": "Royal Holloway University of London",
  "courses": [
    {
      "level": "Masters Program",
      "stream": "??",
      "degree": "??",
      "specialization": "??",
      "course_name": "MBA International Management ",
      "department/school": "??",
      "mode": "??",
      "duration": "1",
      "duration_type": "Year",
      "tuition_fees": "19,22,336",
      "tuition_fee_currency": "INR",
      "tuition_fee_duration_type": "Annual ",
      "application_fee": "18",
      "application_fee_currency": "Pound"
    },
    {
      "level": "Bachelors Program",
      "stream": "??",
      "degree": "??",
      "specialization": "??",
      "course_name": "Business and Management BSc",
      "department/school": "??",
      "mode": "??",
      "duration": "3",
      "duration_type": "Years",
      "tuition_fees": "14,41,752",
      "tuition_fee_currency": "INR",
      "tuition_fee_duration_type": "Annual ",
      "application_fee": "18",
      "application_fee_currency": "Pound"
    },
    {
      "level": "Masters Program",
      "stream": "??",
      "degree": "??",
      "specialization": "??",
      "course_name": "MSc in Finance",
      "department/school": "??",
      "mode": "??",
      "duration": "1",
      "duration_type": "Year",
      "tuition_fees": "15,71,140",
      "tuition_fee_currency": "INR",
      "tuition_fee_duration_type": "Annual ",
      "application_fee": "18",
      "application_fee_currency": "Pound"
    },
    {
      "level": "Masters Program",
      "stream": "??",
      "degree": "??",
      "specialization": "??",
      "course_name": "MSc Project Management",
      "department/school": "??",
      "mode": "??",
      "duration": "1",
      "duration_type": "Year",
      "tuition_fees": "15,71,140",
      "tuition_fee_currency": "INR",
      "tuition_fee_duration_type": "Annual ",
      "application_fee": "18",
      "application_fee_currency": "Pound"
    },
    {
      "level": "Bachelors Program",
      "stream": "??",
      "degree": "??",
      "specialization": "??",
      "course_name": "Physics BSc",
      "department/school": "??",
      "mode": "??",
      "duration": "3",
      "duration_type": "Years",
      "tuition_fees": "14,41,752",
      "tuition_fee_currency": "INR",
      "tuition_fee_duration_type": "Annual ",
      "application_fee": "18",
      "application_fee_currency": "Pound"
    },
    {
      "level": "Bachelors Program",
      "stream": "??",
      "degree": "??",
      "specialization": "??",
      "course_name": "Geology BSc",
      "department/school": "??",
      "mode": "??",
      "duration": "3",
      "duration_type": "Years",
      "tuition_fees": "14,41,752",
      "tuition_fee_currency": "INR",
      "tuition_fee_duration_type": "Annual ",
      "application_fee": "18",
      "application_fee_currency": "Pound"
    }
  ]
}