{
  "name_of_the_university": "Western Connecticut State University",
  "courses": [
    {
      "level": "Masters Program",
      "stream": "??",
      "degree": "??",
      "specialization": "??",
      "course_name": "Master of Business Administration",
      "department/school": "??",
      "mode": "??",
      "duration": "12-14",
      "duration_type": "Months",
      "tuition_fees": "17,40,382",
      "tuition_fee_currency": "INR",
      "tuition_fee_duration_type": "Annual ",
      "application_fee": "50",
      "application_fee_currency": "USD"
    },
    {
      "level": "Bachelors Program",
      "stream": "??",
      "degree": "??",
      "specialization": "??",
      "course_name": "Bachelor of Business Administration in Management Information Systems",
      "department/school": "??",
      "mode": "??",
      "duration": "4",
      "duration_type": "Years",
      "tuition_fees": "17,23,154",
      "tuition_fee_currency": "INR",
      "tuition_fee_duration_type": "Annual ",
      "application_fee": "50",
      "application_fee_currency": "USD"
    },
    {
      "level": "Bachelors Program",
      "stream": "??",
      "degree": "??",
      "specialization": "??",
      "course_name": "Bachelor of Business Administration in Marketing",
      "department/school": "??",
      "mode": "??",
      "duration": "4",
      "duration_type": "Years",
      "tuition_fees": "17,23,154",
      "tuition_fee_currency": "INR",
      "tuition_fee_duration_type": "Annual ",
      "application_fee": "50",
      "application_fee_currency": "USD"
    },
    {
      "level": "Bachelors Program",
      "stream": "??",
      "degree": "??",
      "specialization": "??",
      "course_name": "BBA Cybersecurity",
      "department/school": "??",
      "mode": "??",
      "duration": "4",
      "duration_type": "Years",
      "tuition_fees": "17,23,154",
      "tuition_fee_currency": "INR",
      "tuition_fee_duration_type": "Annual ",
      "application_fee": "50",
      "application_fee_currency": "USD"
    },
    {
      "level": "Bachelors Program",
      "stream": "??",
      "degree": "??",
      "specialization": "??",
      "course_name": "Bachelor of Arts in Social Work",
      "department/school": "??",
      "mode": "??",
      "duration": "4",
      "duration_type": "Years",
      "tuition_fees": "17,23,154",
      "tuition_fee_currency": "INR",
      "tuition_fee_duration_type": "Annual ",
      "application_fee": "50",
      "application_fee_currency": "USD"
    },
    {
      "level": "Bachelors Program",
      "stream": "??",
      "degree": "??",
      "specialization": "??",
      "course_name": "Bachelor of Business Administration in Finance",
      "department/school": "??",
      "mode": "??",
      "duration": "4",
      "duration_type": "Years",
      "tuition_fees": "17,23,154",
      "tuition_fee_currency": "INR",
      "tuition_fee_duration_type": "Annual ",
      "application_fee": "50",
      "application_fee_currency": "USD"
    },
    {
      "level": "Bachelors Program",
      "stream": "??",
      "degree": "??",
      "specialization": "??",
      "course_name": "Bachelor of Business Administration In Accounting",
      "department/school": "??",
      "mode": "??",
      "duration": "4",
      "duration_type": "Years",
      "tuition_fees": "17,23,154",
      "tuition_fee_currency": "INR",
      "tuition_fee_duration_type": "Annual ",
      "application_fee": "50",
      "application_fee_currency": "USD"
    },
    {
      "level": "Masters Program",
      "stream": "??",
      "degree": "??",
      "specialization": "??",
      "course_name": "Master of Fine Arts in Visual Arts",
      "department/school": "??",
      "mode": "??",
      "duration": "2",
      "duration_type": "Years",
      "tuition_fees": "19,83,286",
      "tuition_fee_currency": "INR",
      "tuition_fee_duration_type": "Annual ",
      "application_fee": "50",
      "application_fee_currency": "USD"
    },
    {
      "level": "Masters Program",
      "stream": "??",
      "degree": "??",
      "specialization": "??",
      "course_name": "Master of Arts in Mathematics   ",
      "department/school": "??",
      "mode": "??",
      "duration": "1.5",
      "duration_type": "Years",
      "tuition_fees": "17,40,382",
      "tuition_fee_currency": "INR",
      "tuition_fee_duration_type": "Annual ",
      "application_fee": "50",
      "application_fee_currency": "USD"
    },
    {
      "level": "Bachelors Program",
      "stream": "??",
      "degree": "??",
      "specialization": "??",
      "course_name": "Bachelor of Business Administration in Management",
      "department/school": "??",
      "mode": "??",
      "duration": "4",
      "duration_type": "Years",
      "tuition_fees": "17,23,154",
      "tuition_fee_currency": "INR",
      "tuition_fee_duration_type": "Annual ",
      "application_fee": "50",
      "application_fee_currency": "USD"
    },
    {
      "level": "Masters Program",
      "stream": "??",
      "degree": "??",
      "specialization": "??",
      "course_name": "Master of Science in Education",
      "department/school": "??",
      "mode": "??",
      "duration": "1.5-2",
      "duration_type": "Years",
      "tuition_fees": "17,40,382",
      "tuition_fee_currency": "INR",
      "tuition_fee_duration_type": "Annual ",
      "application_fee": "50",
      "application_fee_currency": "USD"
    }
  ]
}